tayloranalysis/__init__.py
tayloranalysis/cls.py
tayloranalysis/cls3.py
tayloranalysis/model_extension.py
tayloranalysis-0.2.14.dist-info/LICENSE
tayloranalysis-0.2.14.dist-info/METADATA
tayloranalysis-0.2.14.dist-info/WHEEL
tayloranalysis-0.2.14.dist-info/RECORD
