Metadata-Version: 2.1
Name: tayloranalysis
Version: 0.2.14
Summary: Taylorcoefficient Analysis for pytorch models
Home-page: https://github.com/KIT-CMS/tayloranalysis
License: GPL-3.0-only
Keywords: PyTorch,model analysis,Taylor coefficients
Author: Artur Monsch, Lars Sowa
Author-email: lars.sowa@kit.edu,artur.monsch@kit.edu
Requires-Python: >=3.8,<4.0
Classifier: License :: OSI Approved :: GNU General Public License v3 (GPLv3)
Classifier: Programming Language :: Python :: 3
Classifier: Programming Language :: Python :: 3.8
Classifier: Programming Language :: Python :: 3.9
Classifier: Programming Language :: Python :: 3.10
Classifier: Programming Language :: Python :: 3.11
Classifier: Programming Language :: Python :: 3.12
Classifier: Programming Language :: Python :: 3.13
Requires-Dist: torch (>=2.0.0,<3.0.0)
Project-URL: Repository, https://github.com/KIT-CMS/tayloranalysis
